loglib/__init__.py
loglib-1.2.1.dist-info/LICENSE
loglib-1.2.1.dist-info/METADATA
loglib-1.2.1.dist-info/WHEEL
loglib-1.2.1.dist-info/top_level.txt
loglib-1.2.1.dist-info/RECORD
