Metadata-Version: 2.1
Name: loglib
Version: 1.2.1
Summary: A decent logging system with some settings built in
Home-page: https://github.com/teddybear315/loglib
Author: Logan Houston
Author-email: logan.houston4509@gmail.com
License: Free Domain
Platform: UNKNOWN
Classifier: Programming Language :: Python :: 3.9
License-File: LICENSE
Requires-Dist: neotermcolor (>=2.0)
